Metadata-Version: 2.1
Name: work
Version: 1.1.2
Summary: Manual time tracking via a CLI that works similarly to git.
Home-page: https://vauhoch.zett.cc/work/
Author: vauhochzett
Author-email: vauhoch@zett.cc
Requires-Python: >=3.8,<4.0
Classifier: Programming Language :: Python :: 3
Classifier: Programming Language :: Python :: 3.8
Classifier: Programming Language :: Python :: 3.9
Classifier: Programming Language :: Python :: 3.10
Classifier: Programming Language :: Python :: 3.11
Classifier: Programming Language :: Python :: 3.12
